{
  "project_info": {
    "project_number": "688563871107",
    "project_id": "ponderada-de114",
    "storage_bucket": "ponderada-de114.appspot.com"
  },
  "client": [
    {
      "client_info": {
        "mobilesdk_app_id": "1:688563871107:android:d0a7b1618a4bf52e0d2ab6",
        "android_client_info": {
          "package_name": "com.example.todoappforpond"
        }
      },
      "oauth_client": [],
      "api_key": [
        {
          "current_key": "AIzaSyA6kOWq41o9T6GAlivL-dJQwNeSS5sW73I"
        }
      ],
      "services": {
        "appinvite_service": {
          "other_platform_oauth_client": []
        }
      }
    }
  ],
  "configuration_version": "1"
}